<?xml version='1.1' encoding='UTF-8'?>
<scriptler plugin="scriptler@2.9">
  <scriptSet class="sorted-set">
    <comparator class="org.jvnet.hudson.plugins.scriptler.util.ByNameSorter"/>
    <script>
      <id>buildlist.groovy</id>
      <name>buildlist</name>
      <comment>Powerkvm buildlist</comment>
      <parameters/>
      <available>true</available>
      <nonAdministerUsing>false</nonAdministerUsing>
      <onlyMaster>false</onlyMaster>
    </script>
    <script>
      <id>distrolist.groovy</id>
      <name>distrolist</name>
      <comment>distro list</comment>
      <parameters/>
      <available>true</available>
      <nonAdministerUsing>false</nonAdministerUsing>
      <onlyMaster>false</onlyMaster>
    </script>
    <script>
      <id>frmlst.groovy</id>
      <name>frmlst</name>
      <comment>firmware list</comment>
      <parameters/>
      <available>true</available>
      <nonAdministerUsing>false</nonAdministerUsing>
      <onlyMaster>false</onlyMaster>
    </script>
  </scriptSet>
  <disbableRemoteCatalog>false</disbableRemoteCatalog>
  <allowRunScriptPermission>false</allowRunScriptPermission>
  <allowRunScriptEdit>false</allowRunScriptEdit>
</scriptler>